[{"tatami":1,"matches":[{"num":0,"cat":"","first1":"","last1":"","club1":""}]},{"tatami":2,"matches":[{"num":0,"cat":"","first1":"","last1":"","club1":""}]},{"tatami":3,"matches":[{"num":0,"cat":"","first1":"","last1":"","club1":""}]},{"tatami":4,"matches":[{"num":0,"cat":"","first1":"","last1":"","club1":""}]},{"tatami":5,"matches":[{"num":0,"cat":"","first1":"","last1":"","club1":""}]},{"tatami":6,"matches":[{"num":0,"cat":"","first1":"","last1":"","club1":""}]},{"tatami":7,"matches":[{"num":0,"cat":"","first1":"","last1":"","club1":""}]}]