[{"category":"U15 F +63 Pool A","numcomp":5,"clubtext":1,"nameord":1,"competitors":[]},{"category":"U15 F +63 Pool C","numcomp":4,"clubtext":1,"nameord":1,"competitors":[]},{"category":"U15 F +63 Pool D","numcomp":4,"clubtext":1,"nameord":1,"competitors":[]},{"category":"U15 F +63 Pool E","numcomp":4,"clubtext":1,"nameord":1,"competitors":[]},{"category":"U15 F +63 Pool G","numcomp":7,"clubtext":1,"nameord":1,"competitors":[]},{"category":"U15 F +63 Pool N","numcomp":4,"clubtext":1,"nameord":1,"competitors":[]}]